{"trial_id": "0068", "hyperparameters": {"space": [{"class_name": "Int", "config": {"name": "units", "default": null, "conditions": [], "min_value": 16, "max_value": 96, "step": 16, "sampling": "linear"}}, {"class_name": "Choice", "config": {"name": "activation_function", "default": "sigmoid", "conditions": [], "values": ["sigmoid", "tanh"], "ordered": false}}, {"class_name": "Int", "config": {"name": "hidden_layers", "default": null, "conditions": [], "min_value": 1, "max_value": 3, "step": 1, "sampling": "linear"}}, {"class_name": "Float", "config": {"name": "learning_rate", "default": 1e-05, "conditions": [], "min_value": 1e-05, "max_value": 0.1, "step": null, "sampling": "log"}}], "values": {"units": 16, "activation_function": "tanh", "hidden_layers": 3, "learning_rate": 0.00044896982083573897, "tuner/epochs": 17, "tuner/initial_epoch": 6, "tuner/bracket": 2, "tuner/round": 1, "tuner/trial_id": "0058"}}, "metrics": {"metrics": {"loss": {"direction": "min", "observations": [{"value": [0.3348437547683716], "step": 9}]}, "val_loss": {"direction": "min", "observations": [{"value": [0.29663407802581787], "step": 9}]}}}, "score": 0.29663407802581787, "best_step": 9, "status": "COMPLETED", "message": null}