{"ongoing_trials": {}, "hyperparameters": {"space": [{"class_name": "Int", "config": {"name": "units", "default": null, "conditions": [], "min_value": 16, "max_value": 96, "step": 16, "sampling": "linear"}}, {"class_name": "Choice", "config": {"name": "activation_function", "default": "relu", "conditions": [], "values": ["relu"], "ordered": false}}, {"class_name": "Int", "config": {"name": "hidden_layers", "default": null, "conditions": [], "min_value": 1, "max_value": 3, "step": 1, "sampling": "linear"}}, {"class_name": "Float", "config": {"name": "learning_rate", "default": 1e-05, "conditions": [], "min_value": 1e-05, "max_value": 0.1, "step": null, "sampling": "log"}}], "values": {"units": 16, "activation_function": "relu", "hidden_layers": 1, "learning_rate": 1e-05}}, "start_order": ["0000", "0001", "0002", "0003", "0004", "0005", "0006", "0007", "0008", "0009"], "end_order": ["0000", "0001", "0002", "0003", "0004", "0005", "0006", "0007", "0008", "0009"], "run_times": {"0000": 1, "0001": 1, "0002": 1, "0003": 1, "0004": 1, "0005": 1, "0006": 1, "0007": 1, "0008": 1, "0009": 1}, "retry_queue": [], "seed": 7643, "seed_state": 7675, "tried_so_far": ["2bf8577512487cf3348a986c6f9d2bba", "f131b685ff1e1d4f6aa56180d8bb5140", "55d82e3c153935b99945dbf78b980a2b", "0226107c60908719275eec87fe905c22", "c54d5df5fd13a83be8d22ee0e0fdf29c", "d7181cce66b9808571068c6c1f9b2d36", "d995282f1f1c53aa69d111063500cac9", "024bdbc8894893e9855b37d0d9bba71d", "14e277576d511c8ba47fc22ebd7fd5b1", "2439cb6d122777b89ec377e6e5846d2b"], "id_to_hash": {"0000": "f131b685ff1e1d4f6aa56180d8bb5140", "0001": "2bf8577512487cf3348a986c6f9d2bba", "0002": "2439cb6d122777b89ec377e6e5846d2b", "0003": "024bdbc8894893e9855b37d0d9bba71d", "0004": "d995282f1f1c53aa69d111063500cac9", "0005": "d7181cce66b9808571068c6c1f9b2d36", "0006": "14e277576d511c8ba47fc22ebd7fd5b1", "0007": "55d82e3c153935b99945dbf78b980a2b", "0008": "0226107c60908719275eec87fe905c22", "0009": "c54d5df5fd13a83be8d22ee0e0fdf29c"}, "hyperband_iterations": 1, "max_epochs": 5, "min_epochs": 1, "factor": 3, "brackets": [{"bracket_num": 0, "rounds": [[{"past_id": null, "id": "0007"}, {"past_id": null, "id": "0008"}, {"past_id": null, "id": "0009"}]]}], "current_bracket": 0, "current_iteration": 0}